[{"id":0,"user":{"id":0,"name":"Glacier","current_health":12,"max_health":12,"current_stamina":10,"max_stamina":10},"auto_save":false,"saved_screenshot_bytes":"aG9nZSBob2dl","saved_location_name":"HogeHoge Mountain","saved_at":"2024-10-25T13:29:37.138455+09:00"},{"id":1,"user":{"id":0,"name":"Glacier","current_health":12,"max_health":12,"current_stamina":10,"max_stamina":10},"auto_save":true,"saved_screenshot_bytes":"aG9nZSBob2dl","saved_location_name":"HogeHoge Highway","saved_at":"2024-10-25T13:29:37.138459+09:00"},{"id":2,"user":{"id":0,"name":"Glacier","current_health":12,"max_health":12,"current_stamina":10,"max_stamina":10},"auto_save":true,"saved_screenshot_bytes":"aG9nZSBob2dl","saved_location_name":"HogeHoge Island","saved_at":"2024-10-25T13:29:37.138461+09:00"},{"id":3,"user":{"id":0,"name":"Glacier","current_health":12,"max_health":12,"current_stamina":10,"max_stamina":10},"auto_save":false,"saved_screenshot_bytes":"aG9nZSBob2dl","saved_location_name":"HogeHoge Island","saved_at":"2024-10-25T13:29:37.138463+09:00"},{"id":4,"user":{"id":0,"name":"Glacier","current_health":12,"max_health":12,"current_stamina":10,"max_stamina":10},"auto_save":true,"saved_screenshot_bytes":"aG9nZSBob2dl","saved_location_name":"HogeHoge Village","saved_at":"2024-10-25T13:29:37.138465+09:00"},{"id":5,"user":{"id":0,"name":"Glacier","current_health":12,"max_health":12,"current_stamina":10,"max_stamina":10},"auto_save":false,"saved_screenshot_bytes":"aG9nZSBob2dl","saved_location_name":"HogeHoge Castle","saved_at":"2024-10-25T13:29:37.138467+09:00"}]